{
    "text": "использование amvera как основной репозиторий если вы начинаете разработку своего приложения и хотите использовать amvera для хостинга вы можете использовать выделенный нами репозиторий git как основной eval rst admonition подсказка class hint для ознакомления с принципом работы с git рекомендуем эту статью https habr com ru articles 541258 которая упростит работу с нашим сервисом подключение репозитория адрес удаленного репозитория находится на странице репозиторий приложения python config img git main png чтобы склонировать пустой репозиторий shell git clone https git amvera ru имя пользователя транслитерированное имя проекта чтобы подключить удаленный репозиторий амвера к локальному репозиторию shell git remote add origin https git amvera ru имя пользователя транслитерированное имя проекта заполнение репозитория напишите код вашего приложения чтобы его можно было собрать и запустить необходимо наличие файла конфигурации amvera yaml configuration config file md и или dockerfile configuration docker md советуем так же ознакомится с процессом сборки build md и развертывания run md приложения развертывание проекта для инициализации процесса сборки и развертывания приложения достаточно отправить изменения в репозиторий амвера shell git push u origin master на запрос пользователя и пароля укажите имя пользователя и пароль вашей учетной записи amvera eval rst admonition подсказка class hint запущенные инстансы вашего проекта при ошибке сборки не останавливаются и продолжат работать если вы столкнулись с ошибкой или вам что то непонятно ознакомьтесь с разделом частые ошибки git freq errors md при работе с git",
    "metadata": {
        "file_name": "main-origin.md",
        "section_count": 5,
        "section_1": "Использование Amvera как основной репозиторий",
        "section_2": "Подключение репозитория",
        "section_3": "Заполнение репозитория",
        "section_4": "Развертывание проекта",
        "section_5": "Если вы столкнулись с ошибкой или вам что-то непонятно"
    }
}